{
    "metadata": {
        "qaoaLayers": 20,
        "backend_name": "ionq_simulator"
    },
    "result": {
        "instance_id": 66,
        "sampled_distribution": [
            [
                "011001",
                1468
            ],
            [
                "101000",
                989
            ],
            [
                "010010",
                964
            ],
            [
                "010011",
                787
            ],
            [
                "101001",
                762
            ],
            [
                "011010",
                632
            ],
            [
                "100010",
                494
            ],
            [
                "101010",
                463
            ],
            [
                "110000",
                442
            ],
            [
                "000011",
                424
            ],
            [
                "010001",
                402
            ],
            [
                "111000",
                390
            ],
            [
                "100001",
                354
            ],
            [
                "010000",
                253
            ],
            [
                "100011",
                220
            ],
            [
                "001001",
                113
            ],
            [
                "111001",
                113
            ],
            [
                "001011",
                105
            ],
            [
                "011000",
                98
            ],
            [
                "101011",
                89
            ],
            [
                "000010",
                84
            ],
            [
                "100000",
                84
            ],
            [
                "110011",
                69
            ],
            [
                "000001",
                54
            ],
            [
                "110010",
                48
            ],
            [
                "110001",
                40
            ],
            [
                "111011",
                13
            ],
            [
                "011011",
                11
            ],
            [
                "000000",
                10
            ],
            [
                "001000",
                10
            ],
            [
                "001010",
                8
            ],
            [
                "111010",
                7
            ]
        ],
        "num_training_loops": 394,
        "final_training_cost": -26.16259765625,
        "optimal_params": [
            2.633240851354099,
            3.9995552136924597,
            3.828302977350533,
            2.6696588751540062,
            2.4977303352682707,
            2.3885601226359623,
            2.1912873314902717,
            2.588284798330561,
            1.5999079096042805,
            1.7351877517082703,
            2.5758085758696745,
            1.4673977092455182,
            1.268679576250854,
            2.1127883408144386,
            1.9668460642073538,
            0.6503638136977711,
            0.4958455711909469,
            0.4942460539561814,
            0.32862094687740007,
            0.16827310283211294,
            0.8865258873939509,
            0.1697083774103718,
            0.3045924681225472,
            0.49764064902428506,
            0.6115723091161587,
            0.7703024668340628,
            0.9174282486932103,
            1.101603122177509,
            1.2396047545388644,
            1.4302143747918084,
            1.540944603826714,
            1.7977674002512296,
            1.854490037519962,
            2.0005651053010967,
            2.1770140585912308,
            2.343792638632254,
            2.4921404992262453,
            3.6839577863492403,
            2.8389456981506123,
            2.7133842585633476
        ]
    }
}