{
    "metadata": {
        "qaoaLayers": 4,
        "backend_name": "aer_simulator_from(fake_torino)"
    },
    "result": {
        "instance_id": 26,
        "sampled_distribution": [
            [
                "100001",
                1268
            ],
            [
                "011000",
                1208
            ],
            [
                "100000",
                420
            ],
            [
                "010000",
                411
            ],
            [
                "001000",
                392
            ],
            [
                "000001",
                367
            ],
            [
                "111000",
                362
            ],
            [
                "101001",
                349
            ],
            [
                "011001",
                342
            ],
            [
                "110001",
                340
            ],
            [
                "001001",
                267
            ],
            [
                "111001",
                267
            ],
            [
                "010001",
                255
            ],
            [
                "000000",
                227
            ],
            [
                "101000",
                212
            ],
            [
                "110000",
                200
            ],
            [
                "011100",
                190
            ],
            [
                "100011",
                170
            ],
            [
                "011010",
                169
            ],
            [
                "100101",
                164
            ],
            [
                "100100",
                107
            ],
            [
                "010100",
                101
            ],
            [
                "101101",
                97
            ],
            [
                "011101",
                93
            ],
            [
                "111100",
                92
            ],
            [
                "010010",
                90
            ],
            [
                "000101",
                88
            ],
            [
                "100010",
                85
            ],
            [
                "001010",
                81
            ],
            [
                "011011",
                80
            ],
            [
                "110011",
                77
            ],
            [
                "110100",
                69
            ],
            [
                "000100",
                68
            ],
            [
                "001101",
                68
            ],
            [
                "111101",
                66
            ],
            [
                "001100",
                66
            ],
            [
                "101011",
                65
            ],
            [
                "000011",
                65
            ],
            [
                "110101",
                62
            ],
            [
                "010101",
                61
            ],
            [
                "111010",
                61
            ],
            [
                "001011",
                59
            ],
            [
                "011110",
                57
            ],
            [
                "000010",
                57
            ],
            [
                "110010",
                57
            ],
            [
                "101100",
                57
            ],
            [
                "010011",
                56
            ],
            [
                "111011",
                54
            ],
            [
                "101010",
                52
            ],
            [
                "100111",
                32
            ],
            [
                "101111",
                30
            ],
            [
                "000111",
                29
            ],
            [
                "100110",
                26
            ],
            [
                "010110",
                25
            ],
            [
                "110111",
                24
            ],
            [
                "000110",
                23
            ],
            [
                "111111",
                21
            ],
            [
                "011111",
                19
            ],
            [
                "110110",
                19
            ],
            [
                "001110",
                18
            ],
            [
                "101110",
                17
            ],
            [
                "111110",
                17
            ],
            [
                "001111",
                16
            ],
            [
                "010111",
                13
            ]
        ],
        "num_training_loops": 62,
        "final_training_cost": -36.83740234375,
        "optimal_params": [
            3.141392332270996,
            2.5197555517735197,
            1.3367209881171298,
            0.7857495980951303,
            0.000766228882289814,
            1.7854455153568816,
            1.571080546374159,
            2.3563489446233024
        ]
    }
}