{
    "metadata": {
        "qaoaLayers": 2,
        "backend_name": "aer_simulator_from(fake_torino)"
    },
    "result": {
        "instance_id": 23,
        "sampled_distribution": [
            [
                "111000",
                5646
            ],
            [
                "111001",
                613
            ],
            [
                "101000",
                499
            ],
            [
                "111100",
                464
            ],
            [
                "111010",
                437
            ],
            [
                "110000",
                373
            ],
            [
                "011000",
                371
            ],
            [
                "101001",
                123
            ],
            [
                "111101",
                103
            ],
            [
                "011010",
                102
            ],
            [
                "111110",
                99
            ],
            [
                "001000",
                93
            ],
            [
                "101100",
                92
            ],
            [
                "110001",
                92
            ],
            [
                "110010",
                92
            ],
            [
                "011001",
                88
            ],
            [
                "111011",
                78
            ],
            [
                "100000",
                78
            ],
            [
                "011100",
                77
            ],
            [
                "110100",
                69
            ],
            [
                "101010",
                51
            ],
            [
                "010000",
                45
            ],
            [
                "101101",
                21
            ],
            [
                "110101",
                20
            ],
            [
                "001010",
                18
            ],
            [
                "111111",
                18
            ],
            [
                "011011",
                16
            ],
            [
                "011110",
                15
            ],
            [
                "001100",
                15
            ],
            [
                "011101",
                14
            ],
            [
                "010010",
                13
            ],
            [
                "000000",
                13
            ],
            [
                "101110",
                12
            ],
            [
                "001001",
                12
            ],
            [
                "100001",
                12
            ],
            [
                "100100",
                11
            ],
            [
                "110011",
                11
            ],
            [
                "101011",
                10
            ],
            [
                "010001",
                9
            ],
            [
                "010100",
                9
            ],
            [
                "100010",
                9
            ],
            [
                "001110",
                8
            ],
            [
                "110110",
                7
            ],
            [
                "110111",
                7
            ],
            [
                "001101",
                5
            ],
            [
                "100110",
                5
            ],
            [
                "010101",
                4
            ],
            [
                "000001",
                4
            ],
            [
                "101111",
                3
            ],
            [
                "001011",
                3
            ],
            [
                "010011",
                2
            ],
            [
                "011111",
                2
            ],
            [
                "100101",
                2
            ],
            [
                "100111",
                2
            ],
            [
                "000100",
                1
            ],
            [
                "000010",
                1
            ],
            [
                "010110",
                1
            ]
        ],
        "num_training_loops": 37,
        "final_training_cost": -31.53662109375,
        "optimal_params": [
            3.1407190864704755,
            1.5704042071034066,
            0.9988904421454814,
            1.5709981774663546
        ]
    }
}