{
    "metadata": {
        "qaoaLayers": 3,
        "backend_name": "aer_simulator"
    },
    "result": {
        "instance_id": 29,
        "sampled_distribution": [
            [
                "1111",
                5923
            ],
            [
                "1110",
                1214
            ],
            [
                "1011",
                1198
            ],
            [
                "1101",
                734
            ],
            [
                "0111",
                725
            ],
            [
                "0101",
                66
            ],
            [
                "1010",
                55
            ],
            [
                "0110",
                26
            ],
            [
                "1001",
                25
            ],
            [
                "0011",
                18
            ],
            [
                "1100",
                9
            ],
            [
                "0010",
                4
            ],
            [
                "1000",
                2
            ],
            [
                "0100",
                1
            ]
        ],
        "num_training_loops": 58,
        "final_training_cost": -10.74755859375,
        "optimal_params": [
            3.1579917810860056,
            2.1086342956204307,
            1.9308409740704666,
            -0.0023193543195529874,
            1.0517153761287295,
            3.179332109548953
        ]
    }
}